<?xml version="1.0" encoding="utf-8" ?>
<dwsync>
<file name="team-1 2.jpg" server="ftp.site4now.net" local="132780278925789309" remote="132259608000000000" Dst="2" />
<file name="team-1.jpg" server="ftp.site4now.net" local="132780278927136631" remote="132259608000000000" Dst="2" />
<file name="team-2 2.jpg" server="ftp.site4now.net" local="132780278927155655" remote="132259608000000000" Dst="2" />
<file name="team-2.jpg" server="ftp.site4now.net" local="132780278927344144" remote="132259608000000000" Dst="2" />
<file name="team-3 2.jpg" server="ftp.site4now.net" local="132780278928779216" remote="132259608000000000" Dst="2" />
<file name="team-3.jpg" server="ftp.site4now.net" local="132780278928779216" remote="132259608000000000" Dst="2" />
<file name="team-4 2.jpg" server="ftp.site4now.net" local="132780278928847567" remote="132259608000000000" Dst="2" />
<file name="team-5 2.jpg" server="ftp.site4now.net" local="132780278930624480" remote="132259608000000000" Dst="2" />
<file name="team-5.jpg" server="ftp.site4now.net" local="132780278930634246" remote="132259608000000000" Dst="2" />
<file name="team-4.jpg" server="ftp.site4now.net" local="132780278930634246" remote="132259608000000000" Dst="2" />
<file name="team-6 2.jpg" server="ftp.site4now.net" local="132780278932122256" remote="132259608000000000" Dst="2" />
<file name="team-6.jpg" server="ftp.site4now.net" local="132780278932199987" remote="132259608000000000" Dst="2" />
<file name="team-7 2.jpg" server="ftp.site4now.net" local="132780278932199987" remote="132259608000000000" Dst="2" />
<file name="team-7.jpg" server="ftp.site4now.net" local="132780278933564225" remote="132259608000000000" Dst="2" />
<file name="team-8 2.jpg" server="ftp.site4now.net" local="132780278933804368" remote="132259608000000000" Dst="2" />
<file name="team-8.jpg" server="ftp.site4now.net" local="132780278933804368" remote="132259608000000000" Dst="2" />
<file name="team-11 2.jpg" server="ftp.site4now.net" local="132780278935202613" remote="132259608000000000" Dst="2" />
<file name="team-11.jpg" server="ftp.site4now.net" local="132780278935355740" remote="132259608000000000" Dst="2" />
<file name="team-12 2.jpg" server="ftp.site4now.net" local="132780278935355740" remote="132259608000000000" Dst="2" />
<file name="team-12.jpg" server="ftp.site4now.net" local="132780278936653910" remote="132259608000000000" Dst="2" />
<file name="team-13 2.jpg" server="ftp.site4now.net" local="132780278936860924" remote="132259608000000000" Dst="2" />
<file name="team-13.jpg" server="ftp.site4now.net" local="132780278937400103" remote="132259608000000000" Dst="2" />
<file name="team-14.jpg" server="ftp.site4now.net" local="132780278938575364" remote="132259608000000000" Dst="2" />
<file name="team-15 2.jpg" server="ftp.site4now.net" local="132780278938958378" remote="132259608000000000" Dst="2" />
<file name="team-14 2.jpg" server="ftp.site4now.net" local="132780278938967636" remote="132259608000000000" Dst="2" />
<file name="team-15.jpg" server="ftp.site4now.net" local="132780278940418340" remote="132259608000000000" Dst="2" />
<file name="team-17 2.jpg" server="ftp.site4now.net" local="132780278940461507" remote="132259608000000000" Dst="2" />
<file name="team-17.jpg" server="ftp.site4now.net" local="132780278940461507" remote="132259608000000000" Dst="2" />
<file name="team-19 2.jpg" server="ftp.site4now.net" local="132780278941880793" remote="132259608000000000" Dst="2" />
<file name="team-19.jpg" server="ftp.site4now.net" local="132780278942007597" remote="132259608000000000" Dst="2" />
<file name="team-22 2.jpg" server="ftp.site4now.net" local="132780278942007597" remote="132259608000000000" Dst="2" />
<file name="team-22.jpg" server="ftp.site4now.net" local="132780278943297031" remote="132259608000000000" Dst="2" />
<file name="team-23 2.jpg" server="ftp.site4now.net" local="132780278943394151" remote="132259608000000000" Dst="2" />
<file name="team-23.jpg" server="ftp.site4now.net" local="132780278943663809" remote="132259608000000000" Dst="2" />
<file name="team-24 2.jpg" server="ftp.site4now.net" local="132780278945009588" remote="132259608000000000" Dst="2" />
<file name="team-24.jpg" server="ftp.site4now.net" local="132780278945176537" remote="132259608000000000" Dst="2" />
<file name="team-25 2.jpg" server="ftp.site4now.net" local="132780278945176537" remote="132259608000000000" Dst="2" />
<file name="team-26 2.jpg" server="ftp.site4now.net" local="132780278946891338" remote="132259608000000000" Dst="2" />
<file name="team-26.jpg" server="ftp.site4now.net" local="132780278946891338" remote="132259608000000000" Dst="2" />
<file name="team-25.jpg" server="ftp.site4now.net" local="132780278948054911" remote="132259608000000000" Dst="2" />
<file name="team-27 2.jpg" server="ftp.site4now.net" local="132780278948583999" remote="132259608000000000" Dst="2" />
<file name="team-27.jpg" server="ftp.site4now.net" local="132780278948613152" remote="132259608000000000" Dst="2" />
<file name="team-28 2.jpg" server="ftp.site4now.net" local="132780278949867195" remote="132259608000000000" Dst="2" />
<file name="team-28.jpg" server="ftp.site4now.net" local="132780278950286881" remote="132259608000000000" Dst="2" />
<file name="team-29 2.jpg" server="ftp.site4now.net" local="132780278950286881" remote="132259608000000000" Dst="2" />
<file name="team-29.jpg" server="ftp.site4now.net" local="132780278952049348" remote="132259608000000000" Dst="2" />
<file name="team-30 2.jpg" server="ftp.site4now.net" local="132780278952068883" remote="132259608000000000" Dst="2" />
<file name="team-30.jpg" server="ftp.site4now.net" local="132780278952068883" remote="132259608000000000" Dst="2" />
<file name="team-11 2.jpg" server="win5135.site4now.net" local="132881244972845553" remote="132260468400000000" Dst="1" />
<file name="team-1 2.jpg" server="win5135.site4now.net" local="132881244973045440" remote="132260461200000000" Dst="1" />
<file name="team-1.jpg" server="win5135.site4now.net" local="132881244973185355" remote="132260461200000000" Dst="1" />
<file name="team-11.jpg" server="win5135.site4now.net" local="132881244973844975" remote="132260461200000000" Dst="1" />
<file name="team-12 2.jpg" server="win5135.site4now.net" local="132881244973924931" remote="132260461200000000" Dst="1" />
<file name="team-12.jpg" server="win5135.site4now.net" local="132881244974044866" remote="132260468400000000" Dst="1" />
<file name="team-13 2.jpg" server="win5135.site4now.net" local="132881244974684496" remote="132260461200000000" Dst="1" />
<file name="team-13.jpg" server="win5135.site4now.net" local="132881244974774442" remote="132260461200000000" Dst="1" />
<file name="team-14 2.jpg" server="win5135.site4now.net" local="132881244974774442" remote="132260461200000000" Dst="1" />
<file name="team-14.jpg" server="win5135.site4now.net" local="132881244975543999" remote="132260461200000000" Dst="1" />
<file name="team-15 2.jpg" server="win5135.site4now.net" local="132881244975703906" remote="132260461200000000" Dst="1" />
<file name="team-15.jpg" server="win5135.site4now.net" local="132881244975703906" remote="132260468400000000" Dst="1" />
<file name="team-17 2.jpg" server="win5135.site4now.net" local="132881244976493455" remote="132260461200000000" Dst="1" />
<file name="team-17.jpg" server="win5135.site4now.net" local="132881244976653366" remote="132260461200000000" Dst="1" />
<file name="team-19 2.jpg" server="win5135.site4now.net" local="132881244976913206" remote="132260461200000000" Dst="1" />
<file name="team-19.jpg" server="win5135.site4now.net" local="132881244977223029" remote="132260461200000000" Dst="1" />
<file name="team-22 2.jpg" server="win5135.site4now.net" local="132881244978042562" remote="132260461200000000" Dst="1" />
<file name="team-2 2.jpg" server="win5135.site4now.net" local="132881244978072541" remote="132260461200000000" Dst="1" />
<file name="team-2.jpg" server="win5135.site4now.net" local="132881244978232463" remote="132260461200000000" Dst="1" />
<file name="team-22.jpg" server="win5135.site4now.net" local="132881244978872080" remote="132260461200000000" Dst="1" />
<file name="team-23 2.jpg" server="win5135.site4now.net" local="132881244979002003" remote="132260461200000000" Dst="1" />
<file name="team-23.jpg" server="win5135.site4now.net" local="132881244979002003" remote="132260468400000000" Dst="1" />
<file name="team-24 2.jpg" server="win5135.site4now.net" local="132881244979661622" remote="132260461200000000" Dst="1" />
<file name="team-24.jpg" server="win5135.site4now.net" local="132881244979921467" remote="132260461200000000" Dst="1" />
<file name="team-25 2.jpg" server="win5135.site4now.net" local="132881244980481148" remote="132260461200000000" Dst="1" />
<file name="team-25.jpg" server="win5135.site4now.net" local="132881244980481148" remote="132260461200000000" Dst="1" />
<file name="team-26 2.jpg" server="win5135.site4now.net" local="132881244980840938" remote="132260461200000000" Dst="1" />
<file name="team-26.jpg" server="win5135.site4now.net" local="132881244981410636" remote="132260461200000000" Dst="1" />
<file name="team-27 2.jpg" server="win5135.site4now.net" local="132881244981410636" remote="132260461200000000" Dst="1" />
<file name="team-27.jpg" server="win5135.site4now.net" local="132881244981580543" remote="132260461200000000" Dst="1" />
<file name="team-28 2.jpg" server="win5135.site4now.net" local="132881244982249255" remote="132260461200000000" Dst="1" />
<file name="team-28.jpg" server="win5135.site4now.net" local="132881244982339206" remote="132260461200000000" Dst="1" />
<file name="team-29 2.jpg" server="win5135.site4now.net" local="132881244982339206" remote="132260468400000000" Dst="1" />
<file name="team-29.jpg" server="win5135.site4now.net" local="132881244983058981" remote="132260461200000000" Dst="1" />
<file name="team-3 2.jpg" server="win5135.site4now.net" local="132881244983604067" remote="132260461200000000" Dst="1" />
<file name="team-30 2.jpg" server="win5135.site4now.net" local="132881244983854123" remote="132260461200000000" Dst="1" />
<file name="team-3.jpg" server="win5135.site4now.net" local="132881244983983980" remote="132260461200000000" Dst="1" />
<file name="team-30.jpg" server="win5135.site4now.net" local="132881244984522089" remote="132260461200000000" Dst="1" />
<file name="team-4 2.jpg" server="win5135.site4now.net" local="132881244985020165" remote="132260461200000000" Dst="1" />
<file name="team-4.jpg" server="win5135.site4now.net" local="132881244985349886" remote="132260461200000000" Dst="1" />
<file name="team-5 2.jpg" server="win5135.site4now.net" local="132881244985829670" remote="132260461200000000" Dst="1" />
<file name="team-5.jpg" server="win5135.site4now.net" local="132881244986445568" remote="132260461200000000" Dst="1" />
<file name="team-6 2.jpg" server="win5135.site4now.net" local="132881244986600569" remote="132260461200000000" Dst="1" />
<file name="team-6.jpg" server="win5135.site4now.net" local="132881244987107565" remote="132260468400000000" Dst="1" />
<file name="team-7 2.jpg" server="win5135.site4now.net" local="132881244987842967" remote="132260461200000000" Dst="1" />
<file name="team-7.jpg" server="win5135.site4now.net" local="132881244988012872" remote="132260461200000000" Dst="1" />
<file name="team-8 2.jpg" server="win5135.site4now.net" local="132881244988487005" remote="132260461200000000" Dst="1" />
<file name="team-8.jpg" server="win5135.site4now.net" local="132881244989304842" remote="132260468400000000" Dst="1" />
</dwsync>