<?xml version="1.0" encoding="utf-8" ?>
<dwsync>
<file name="course-1 2.jpg" server="ftp.site4now.net" local="132780277031957897" remote="132259608000000000" Dst="2" />
<file name="course-1.jpg" server="ftp.site4now.net" local="132780277032153029" remote="132259608000000000" Dst="2" />
<file name="course-2 2.jpg" server="ftp.site4now.net" local="132780277032518458" remote="132259608000000000" Dst="2" />
<file name="course-3 2.jpg" server="ftp.site4now.net" local="132780277033842026" remote="132259608000000000" Dst="2" />
<file name="course-2.jpg" server="ftp.site4now.net" local="132780277034066446" remote="132259608000000000" Dst="2" />
<file name="course-3.jpg" server="ftp.site4now.net" local="132780277034662017" remote="132259608000000000" Dst="2" />
<file name="course-4 2.jpg" server="ftp.site4now.net" local="132780277035643998" remote="132259608000000000" Dst="2" />
<file name="course-4.jpg" server="ftp.site4now.net" local="132780277035966181" remote="132259608000000000" Dst="2" />
<file name="course-5 2.jpg" server="ftp.site4now.net" local="132780277037438676" remote="132259608000000000" Dst="2" />
<file name="course-5.jpg" server="ftp.site4now.net" local="132780277037770658" remote="132259608000000000" Dst="2" />
<file name="course-6 2.jpg" server="ftp.site4now.net" local="132780277037780189" remote="132259608000000000" Dst="2" />
<file name="course-7 2.jpg" server="ftp.site4now.net" local="132780277039460145" remote="132259608000000000" Dst="2" />
<file name="course-6.jpg" server="ftp.site4now.net" local="132780277039858520" remote="132259608000000000" Dst="2" />
<file name="course-7.jpg" server="ftp.site4now.net" local="132780277039858520" remote="132259608000000000" Dst="2" />
<file name="course-8 2.jpg" server="ftp.site4now.net" local="132780277042213913" remote="132259608000000000" Dst="2" />
<file name="course-8.jpg" server="ftp.site4now.net" local="132780277042619773" remote="132259608000000000" Dst="2" />
<file name="course-1 2.jpg" server="win5135.site4now.net" local="132881243678591263" remote="132260465400000000" Dst="1" />
<file name="course-1.jpg" server="win5135.site4now.net" local="132881243679011028" remote="132260465400000000" Dst="1" />
<file name="course-2 2.jpg" server="win5135.site4now.net" local="132881243679110963" remote="132260465400000000" Dst="1" />
<file name="course-2.jpg" server="win5135.site4now.net" local="132881243679410788" remote="132260465400000000" Dst="1" />
<file name="course-3.jpg" server="win5135.site4now.net" local="132881243679870523" remote="132260465400000000" Dst="1" />
<file name="course-3 2.jpg" server="win5135.site4now.net" local="132881243679960493" remote="132260465400000000" Dst="1" />
<file name="course-4 2.jpg" server="win5135.site4now.net" local="132881243680360239" remote="132260465400000000" Dst="1" />
<file name="course-4.jpg" server="win5135.site4now.net" local="132881243680600109" remote="132260465400000000" Dst="1" />
<file name="course-5 2.jpg" server="win5135.site4now.net" local="132881243680820008" remote="132260465400000000" Dst="1" />
<file name="course-5.jpg" server="win5135.site4now.net" local="132881243681099824" remote="132260465400000000" Dst="1" />
<file name="course-6 2.jpg" server="win5135.site4now.net" local="132881243681329732" remote="132260465400000000" Dst="1" />
<file name="course-6.jpg" server="win5135.site4now.net" local="132881243681579549" remote="132260465400000000" Dst="1" />
<file name="course-7 2.jpg" server="win5135.site4now.net" local="132881243681889359" remote="132260465400000000" Dst="1" />
<file name="course-7.jpg" server="win5135.site4now.net" local="132881243682139220" remote="132260465400000000" Dst="1" />
<file name="course-8 2.jpg" server="win5135.site4now.net" local="132881243682389072" remote="132260465400000000" Dst="1" />
<file name="course-8.jpg" server="win5135.site4now.net" local="132881243682658915" remote="132260465400000000" Dst="1" />
</dwsync>