<?xml version="1.0" encoding="utf-8" ?>
<dwsync>
<file name="blog-construction-1 2.jpg" server="ftp.site4now.net" local="132780276986168384" remote="132259608000000000" Dst="2" />
<file name="blog-construction-1.jpg" server="ftp.site4now.net" local="132780276986550408" remote="132259608000000000" Dst="2" />
<file name="blog-construction-2 2.jpg" server="ftp.site4now.net" local="132780276987730573" remote="132259608000000000" Dst="2" />
<file name="blog-construction-2.jpg" server="ftp.site4now.net" local="132780276987740643" remote="132259608000000000" Dst="2" />
<file name="blog-construction-3 2.jpg" server="ftp.site4now.net" local="132780276987740643" remote="132259608000000000" Dst="2" />
<file name="blog-construction-3.jpg" server="ftp.site4now.net" local="132780276988824194" remote="132259608000000000" Dst="2" />
<file name="blog-construction-1 2.jpg" server="win5135.site4now.net" local="132881243649883558" remote="132260466000000000" Dst="1" />
<file name="blog-construction-1.jpg" server="win5135.site4now.net" local="132881243649973509" remote="132260466000000000" Dst="1" />
<file name="blog-construction-2.jpg" server="win5135.site4now.net" local="132881243650932957" remote="132260466000000000" Dst="1" />
<file name="blog-construction-2 2.jpg" server="win5135.site4now.net" local="132881243651102857" remote="132260466000000000" Dst="1" />
<file name="blog-construction-3 2.jpg" server="win5135.site4now.net" local="132881243651212795" remote="132260466000000000" Dst="1" />
<file name="blog-construction-3.jpg" server="win5135.site4now.net" local="132881243651752479" remote="132260466000000000" Dst="1" />
</dwsync>