<?xml version="1.0" encoding="utf-8" ?>
<dwsync>
<file name="product1 2.jpg" server="ftp.site4now.net" local="132780277916150398" remote="132259608000000000" Dst="2" />
<file name="product1.jpg" server="ftp.site4now.net" local="132780277916619217" remote="132259608000000000" Dst="2" />
<file name="product2 2.jpg" server="ftp.site4now.net" local="132780277918083707" remote="132259608000000000" Dst="2" />
<file name="product2.jpg" server="ftp.site4now.net" local="132780277918083707" remote="132259608000000000" Dst="2" />
<file name="product3 2.jpg" server="ftp.site4now.net" local="132780277918552163" remote="132259608000000000" Dst="2" />
<file name="product3.jpg" server="ftp.site4now.net" local="132780277919840921" remote="132259608000000000" Dst="2" />
<file name="product4 2.jpg" server="ftp.site4now.net" local="132780277920026427" remote="132259608000000000" Dst="2" />
<file name="product4.jpg" server="ftp.site4now.net" local="132780277920319321" remote="132259608000000000" Dst="2" />
<file name="product5 2.jpg" server="ftp.site4now.net" local="132780277921969348" remote="132259608000000000" Dst="2" />
<file name="product5.jpg" server="ftp.site4now.net" local="132780277922154825" remote="132259608000000000" Dst="2" />
<file name="product6 2.jpg" server="ftp.site4now.net" local="132780277922164590" remote="132259608000000000" Dst="2" />
<file name="product6.jpg" server="ftp.site4now.net" local="132780277924009847" remote="132259608000000000" Dst="2" />
<file name="product7 2.jpg" server="ftp.site4now.net" local="132780277924009847" remote="132259608000000000" Dst="2" />
<file name="product7.jpg" server="ftp.site4now.net" local="132780277924380851" remote="132259608000000000" Dst="2" />
<file name="product8.jpg" server="ftp.site4now.net" local="132780277926089437" remote="132259608000000000" Dst="2" />
<file name="product9 2.jpg" server="ftp.site4now.net" local="132780277926343415" remote="132259608000000000" Dst="2" />
<file name="product8 2.jpg" server="ftp.site4now.net" local="132780277926353046" remote="132259608000000000" Dst="2" />
<file name="product9.jpg" server="ftp.site4now.net" local="132780277928549780" remote="132259608000000000" Dst="2" />
<file name="product1 2.jpg" server="win5135.site4now.net" local="132881244201547042" remote="132260467200000000" Dst="1" />
<file name="product1.jpg" server="win5135.site4now.net" local="132881244202465064" remote="132260467200000000" Dst="1" />
<file name="product2.jpg" server="win5135.site4now.net" local="132881244202495052" remote="132260467200000000" Dst="1" />
<file name="product2 2.jpg" server="win5135.site4now.net" local="132881244202834956" remote="132260467200000000" Dst="1" />
<file name="product3 2.jpg" server="win5135.site4now.net" local="132881244203193178" remote="132260467200000000" Dst="1" />
<file name="product3.jpg" server="win5135.site4now.net" local="132881244203293125" remote="132260467200000000" Dst="1" />
<file name="product4 2.jpg" server="win5135.site4now.net" local="132881244203522987" remote="132260467200000000" Dst="1" />
<file name="product4.jpg" server="win5135.site4now.net" local="132881244203881917" remote="132260467200000000" Dst="1" />
<file name="product5 2.jpg" server="win5135.site4now.net" local="132881244204051821" remote="132260467200000000" Dst="1" />
<file name="product5.jpg" server="win5135.site4now.net" local="132881244204533725" remote="132260467200000000" Dst="1" />
<file name="product6 2.jpg" server="win5135.site4now.net" local="132881244204768124" remote="132260467200000000" Dst="1" />
<file name="product6.jpg" server="win5135.site4now.net" local="132881244204768124" remote="132260467200000000" Dst="1" />
<file name="product7 2.jpg" server="win5135.site4now.net" local="132881244205433667" remote="132260467200000000" Dst="1" />
<file name="product7.jpg" server="win5135.site4now.net" local="132881244205453567" remote="132260467200000000" Dst="1" />
<file name="product8 2.jpg" server="win5135.site4now.net" local="132881244205623467" remote="132260467200000000" Dst="1" />
<file name="product8.jpg" server="win5135.site4now.net" local="132881244206312294" remote="132260467200000000" Dst="1" />
<file name="product9.jpg" server="win5135.site4now.net" local="132881244206322291" remote="132260467200000000" Dst="1" />
<file name="product9 2.jpg" server="win5135.site4now.net" local="132881244206802008" remote="132260467200000000" Dst="1" />
</dwsync>