<?xml version="1.0" encoding="utf-8" ?>
<dwsync>
<file name="cart-product1 2.jpg" server="ftp.site4now.net" local="132780278059183026" remote="132259608000000000" Dst="2" />
<file name="cart-product1.jpg" server="ftp.site4now.net" local="132780278059475878" remote="132259608000000000" Dst="2" />
<file name="cart-product2 2.jpg" server="ftp.site4now.net" local="132780278059475878" remote="132259608000000000" Dst="2" />
<file name="cart-product2.jpg" server="ftp.site4now.net" local="132780278061360064" remote="132259608000000000" Dst="2" />
<file name="product1 2.jpg" server="ftp.site4now.net" local="132780278061360064" remote="132259608000000000" Dst="2" />
<file name="product1.jpg" server="ftp.site4now.net" local="132780278061369821" remote="132259608000000000" Dst="2" />
<file name="product2 2.jpg" server="ftp.site4now.net" local="132780278063016723" remote="132259608000000000" Dst="2" />
<file name="product2.jpg" server="ftp.site4now.net" local="132780278063016723" remote="132259608000000000" Dst="2" />
<file name="product3 2.jpg" server="ftp.site4now.net" local="132780278063280337" remote="132259608000000000" Dst="2" />
<file name="product3.jpg" server="ftp.site4now.net" local="132780278065037864" remote="132259608000000000" Dst="2" />
<file name="product4 2.jpg" server="ftp.site4now.net" local="132780278065496604" remote="132259608000000000" Dst="2" />
<file name="product4.jpg" server="ftp.site4now.net" local="132780278065506365" remote="132259608000000000" Dst="2" />
<file name="product5 2.jpg" server="ftp.site4now.net" local="132780278067693345" remote="132259608000000000" Dst="2" />
<file name="product5.jpg" server="ftp.site4now.net" local="132780278067703115" remote="132259608000000000" Dst="2" />
<file name="product6 2.jpg" server="ftp.site4now.net" local="132780278068181512" remote="132259608000000000" Dst="2" />
<file name="product6.jpg" server="ftp.site4now.net" local="132780278069665524" remote="132259608000000000" Dst="2" />
<file name="product7 2.jpg" server="ftp.site4now.net" local="132780278069665524" remote="132259608000000000" Dst="2" />
<file name="product7.jpg" server="ftp.site4now.net" local="132780278069982616" remote="132259608000000000" Dst="2" />
<file name="product8 2.jpg" server="ftp.site4now.net" local="132780278071515446" remote="132259608000000000" Dst="2" />
<file name="product8.jpg" server="ftp.site4now.net" local="132780278071657651" remote="132259608000000000" Dst="2" />
<file name="product9 2.jpg" server="ftp.site4now.net" local="132780278072038281" remote="132259608000000000" Dst="2" />
<file name="product9.jpg" server="ftp.site4now.net" local="132780278073619957" remote="132259608000000000" Dst="2" />
<file name="product10 2.jpg" server="ftp.site4now.net" local="132780278073619957" remote="132259608000000000" Dst="2" />
<file name="product10.jpg" server="ftp.site4now.net" local="132780278073727334" remote="132259608000000000" Dst="2" />
<file name="product11 2.jpg" server="ftp.site4now.net" local="132780278075308994" remote="132259608000000000" Dst="2" />
<file name="product11.jpg" server="ftp.site4now.net" local="132780278075474973" remote="132259608000000000" Dst="2" />
<file name="product12 2.jpg" server="ftp.site4now.net" local="132780278075474973" remote="132259608000000000" Dst="2" />
<file name="product12.jpg" server="ftp.site4now.net" local="132780278077085910" remote="132259608000000000" Dst="2" />
<file name="cart-product1.jpg" server="win5135.site4now.net" local="132881244296812211" remote="132260467200000000" Dst="1" />
<file name="cart-product1 2.jpg" server="win5135.site4now.net" local="132881244296882166" remote="132260467200000000" Dst="1" />
<file name="cart-product2 2.jpg" server="win5135.site4now.net" local="132881244296992117" remote="132260467200000000" Dst="1" />
<file name="cart-product2.jpg" server="win5135.site4now.net" local="132881244297631736" remote="132260467200000000" Dst="1" />
<file name="product1 2.jpg" server="win5135.site4now.net" local="132881244297681716" remote="132260467200000000" Dst="1" />
<file name="product1.jpg" server="win5135.site4now.net" local="132881244297701709" remote="132260467200000000" Dst="1" />
<file name="product10.jpg" server="win5135.site4now.net" local="132881244298551209" remote="132260467200000000" Dst="1" />
<file name="product10 2.jpg" server="win5135.site4now.net" local="132881244298651149" remote="132260467200000000" Dst="1" />
<file name="product11.jpg" server="win5135.site4now.net" local="132881244299384363" remote="132260467200000000" Dst="1" />
<file name="product12 2.jpg" server="win5135.site4now.net" local="132881244299444330" remote="132260467200000000" Dst="1" />
<file name="product12.jpg" server="win5135.site4now.net" local="132881244300113662" remote="132260467200000000" Dst="1" />
<file name="product2 2.jpg" server="win5135.site4now.net" local="132881244300263466" remote="132260467200000000" Dst="1" />
<file name="product2.jpg" server="win5135.site4now.net" local="132881244300755900" remote="132260467200000000" Dst="1" />
<file name="product3.jpg" server="win5135.site4now.net" local="132881244301745619" remote="132260467200000000" Dst="1" />
<file name="product3 2.jpg" server="win5135.site4now.net" local="132881244302673155" remote="132260467200000000" Dst="1" />
<file name="product11 2.jpg" server="win5135.site4now.net" local="132881244303382761" remote="132260467200000000" Dst="1" />
<file name="product4 2.jpg" server="win5135.site4now.net" local="132881244303382761" remote="132260467200000000" Dst="1" />
<file name="product4.jpg" server="win5135.site4now.net" local="132881244303392766" remote="132260467200000000" Dst="1" />
<file name="product5 2.jpg" server="win5135.site4now.net" local="132881244304342234" remote="132260467200000000" Dst="1" />
<file name="product5.jpg" server="win5135.site4now.net" local="132881244304522110" remote="132260467200000000" Dst="1" />
<file name="product6 2.jpg" server="win5135.site4now.net" local="132881244304642038" remote="132260467200000000" Dst="1" />
<file name="product6.jpg" server="win5135.site4now.net" local="132881244305021815" remote="132260467200000000" Dst="1" />
<file name="product7 2.jpg" server="win5135.site4now.net" local="132881244305261675" remote="132260467200000000" Dst="1" />
<file name="product7.jpg" server="win5135.site4now.net" local="132881244305261675" remote="132260467200000000" Dst="1" />
<file name="product8 2.jpg" server="win5135.site4now.net" local="132881244305841343" remote="132260467200000000" Dst="1" />
<file name="product8.jpg" server="win5135.site4now.net" local="132881244305861331" remote="132260467200000000" Dst="1" />
<file name="product9 2.jpg" server="win5135.site4now.net" local="132881244306011245" remote="132260467200000000" Dst="1" />
<file name="product9.jpg" server="win5135.site4now.net" local="132881244306560926" remote="132260467200000000" Dst="1" />
</dwsync>